pyrocket_launch-0.2.0.dist-info/METADATA
pyrocket_launch-0.2.0.dist-info/WHEEL
pyrocket_launch/__init__.py
pyrocket_launch/main.py
pyrocket_launch/moon.png
pyrocket_launch/orange_planet.png
pyrocket_launch/planet.png
pyrocket_launch/purple_planet.png
pyrocket_launch/rocket.png
pyrocket_launch-0.2.0.dist-info/RECORD
